qiyu_api/__init__.py
qiyu_api/ali_sms_api/__init__.py
qiyu_api/ali_sms_api/base.py
qiyu_api/ali_sms_api/gen.py
qiyu_api/ali_sms_api/py_test_sms.py
qiyu_api/ali_top/__init__.py
qiyu_api/ali_top/args/__init__.py
qiyu_api/ali_top/args/product_get.py
qiyu_api/ali_top/args/tbk_sc_publisher_info_save.py
qiyu_api/ali_top/args/time_get.py
qiyu_api/ali_top/args/top_auth_token_create.py
qiyu_api/ali_top/args/user_seller_get.py
qiyu_api/ali_top/async_api.py
qiyu_api/ali_top/base_api.py
qiyu_api/ali_top/dt/__init__.py
qiyu_api/ali_top/dt/top_auth_token_create_token_result.py
qiyu_api/ali_top/exceptions.py
qiyu_api/ali_top/resp/__init__.py
qiyu_api/ali_top/resp/tbk_sc_publisher_info_save.py
qiyu_api/ali_top/resp/time_get.py
qiyu_api/ali_top/resp/top_auth_token_create.py
qiyu_api/ali_top/sync_api.py
qiyu_api/apns_sdk_py/__init__.py
qiyu_api/apns_sdk_py/api_async.py
qiyu_api/apns_sdk_py/api_sync.py
qiyu_api/apns_sdk_py/dt.py
qiyu_api/dtk_api/__init__.py
qiyu_api/dtk_api/api_async.py
qiyu_api/dtk_api/api_std.py
qiyu_api/dtk_api/api_sync.py
qiyu_api/dtk_api/base.py
qiyu_api/dtk_api/dt_resp.py
qiyu_api/dtk_api/dt_resp_v2.py
qiyu_api/dtk_api/gen.py
qiyu_api/dtk_api/test_demo.py
qiyu_api/dtk_api/test_dtk.py
qiyu_api/dtk_api/test_gen.py
qiyu_api/dtk_api/test_shared.py
qiyu_api/dtk_api/test_std.py
qiyu_api/dtk_api/test_type.py
qiyu_api/dtk_api/test_value.py
qiyu_api/mob_api/__init__.py
qiyu_api/mob_api/mob_push.py
qiyu_api/mob_api/mob_push_base.py
qiyu_api/mob_api/mob_push_sync.py
qiyu_api/mob_api/mob_sms.py
qiyu_api/py_apple_signin/__init__.py
qiyu_api/py_apple_signin/async_api.py
qiyu_api/py_apple_signin/dt.py
qiyu_api/py_apple_signin/shared.py
qiyu_api/py_apple_signin/sync_api.py
qiyu_api/tbk_api/__init__.py
qiyu_api/tbk_api/dt.py
qiyu_api/ztk_api/__init__.py
qiyu_api/ztk_api/auth_account_args.py
qiyu_api/ztk_api/bang_dan_tui_jian_args.py
qiyu_api/ztk_api/base_args.py
qiyu_api/ztk_api/batch_item_args.py
qiyu_api/ztk_api/batch_item_model.py
qiyu_api/ztk_api/batch_item_resp.py
qiyu_api-0.7.6.dist-info/WHEEL
qiyu_api-0.7.6.dist-info/METADATA
qiyu_api-0.7.6.dist-info/RECORD
