Metadata-Version: 2.1
Name: qiyu-api
Version: 0.7.6
Summary: 奇遇科技 Python API 合集
Home-page: https://oss.qiyutech.tech/
Author: dev
Author-email: dev@qiyutech.tech
Requires-Python: >=3.9,<4.0
Classifier: Programming Language :: Python :: 3
Classifier: Programming Language :: Python :: 3.10
Classifier: Programming Language :: Python :: 3.9
Requires-Dist: aiohttp (>=3.7.4,<4)
Requires-Dist: cryptography (>=3.4)
Requires-Dist: pydantic (>=1.7,<2)
Requires-Dist: pydes (>=2,<3)
Requires-Dist: pyjwt (>=2.0,<3)
Requires-Dist: requests (>=2.25,<3)
Requires-Dist: structlog (>=21,<22)
Project-URL: Repository, https://github.com/QiYuTechDev/qiyu-api
